django_tenants_smart_executor/__init__.py
django_tenants_smart_executor/executors.py
django_tenants_smart_executor-0.1.0.dist-info/LICENSE
django_tenants_smart_executor-0.1.0.dist-info/METADATA
django_tenants_smart_executor-0.1.0.dist-info/WHEEL
django_tenants_smart_executor-0.1.0.dist-info/RECORD
