Metadata-Version: 2.3
Name: django-tenants-smart-executor
Version: 0.1.0
Summary: Executors for django-tenants which check whether any migrations need running before running them, making it faster.
License: MIT
Keywords: django,django-tenants,migrations
Author: Mikuláš Poul
Author-email: mikulas.poul@xelix.com
Requires-Python: >=3.9
Classifier: Programming Language :: Python
Classifier: Programming Language :: Python :: 3
Classifier: Programming Language :: Python :: 3.9
Classifier: Programming Language :: Python :: 3.10
Classifier: Programming Language :: Python :: 3.11
Classifier: Programming Language :: Python :: 3.12
Classifier: Programming Language :: Python :: 3.13
Classifier: Development Status :: 5 - Production/Stable
Classifier: License :: OSI Approved :: MIT License
Classifier: Framework :: Django
Requires-Dist: django-tenants (>=3.8)
Project-URL: Repository, https://github.com/xelixdev/django-tenants-smart-executor
